igcanvas/__init__.py
igcanvas-0.0.1.dist-info/METADATA
igcanvas-0.0.1.dist-info/WHEEL
igcanvas-0.0.1.dist-info/top_level.txt
igcanvas-0.0.1.dist-info/RECORD
